django_data_import/__init__.py
django_data_import/forms.py
django_data_import/mixins.py
django_data_import/templates/admin/django_data_import/base.html
django_data_import/templates/admin/django_data_import/change_list_import.html
django_data_import/templates/admin/django_data_import/form_field.html
django_data_import/templates/admin/django_data_import/import.html
Django_Data_Import-1.0.2.dist-info/DESCRIPTION.rst
Django_Data_Import-1.0.2.dist-info/METADATA
Django_Data_Import-1.0.2.dist-info/metadata.json
Django_Data_Import-1.0.2.dist-info/pbr.json
Django_Data_Import-1.0.2.dist-info/RECORD
Django_Data_Import-1.0.2.dist-info/top_level.txt
Django_Data_Import-1.0.2.dist-info/WHEEL
