Metadata-Version: 2.0
Name: Django-Data-Import
Version: 1.0.2
Summary: Data import from CVS file to Django Model
Home-page: https://github.com/1st/django-data-import
Author: Anton Danilchenko
Author-email: anton@danilchenko.me
License: MIT
Keywords: django csv data import
Platform: any
Classifier: Development Status :: 4 - Beta
Classifier: Environment :: Web Environment
Classifier: Intended Audience :: Developers
Classifier: License :: OSI Approved :: MIT License
Classifier: Operating System :: OS Independent
Classifier: Programming Language :: Python
Classifier: Programming Language :: Python :: 2
Classifier: Programming Language :: Python :: 2.7
Classifier: Programming Language :: Python :: 3
Classifier: Programming Language :: Python :: 3.3
Classifier: Programming Language :: Python :: 3.4
Classifier: Topic :: Internet :: WWW/HTTP :: Dynamic Content
Classifier: Topic :: Software Development :: Libraries :: Python Modules
Requires-Dist: django (>=1.7)
